{
  "name": "Phoebe May",
  "age": 40,
  "address": {
    "street": "Erunej Point",
    "city": "Hejsugor",
    "state": "OK",
    "zip": "20019"
  },
  "contact": {
    "phone": "(862) 836-2527",
    "servicePhone": "800677782"
  },
  "birthday": "2003-08-25T16:29:50.112Z",
  "ip": "162.247.206.242",
  "foo": "bar",
  "profile": {
    "about": "Sit puk gelab uchapivi tozu wojiskiv odci gogikat tekowar fo wa buj bebanpuk jagi sakug buzdipsoj. Ohupe bokejvu raho giwlav nik zocfi ejlijzut ukimoiw taj ne pifdokeb adinogip ga livusjod kivvam. Ni raariler ibiros nufgon wewwag mi me incoeho vanka cehi muposo wihseguv. Naosfuh re piw hi jilkubzi piewe kenlig va ojtupos lu fohvok acovez ocbep ih uke. Koherat ruzino dinag tat gumece tadcok zagohag jawofki kufefuw ultusaz gus or lavon ina culu ke ulekufni pap. Fu sew tehadjah me cofgoz daihvo pa poabeeh gabgeba evaze tucrim okotig mek sot lewege we owe jejinlu.",
    "bio": "Mehhe cufrippiv us urure olu rajbu eza te wezorku pac supekniv rotod. Duweve feog fizdutum na ehojo enkefe ovrip tafim ru har efdo rera ak. Ociwipca mimedjow avboj fawed dezgici ka ba ludre ac nivsi nuc cias do efupasso idzon sinci. Aw tehilkos je obukogag tegu hofkuj bitracmil lifa tezo nawebzih berhihud somedeof ijezaemo. Lebsumjo mi ti dac sig sumfowaze ho jow ihepu li seca gefedu japudiw salzop ruralga."
  },
  "apiKey": "18e3eff8c06cc1265645630c1c8b3577b7c5ee8703021cf2929ca09fb4977d31",
  "currency": {
    "code": "ILS",
    "name": "Israel Shekel"
  }
}