{
  "name": "Christopher Reyes",
  "age": 35,
  "address": {
    "street": "Nebir Grove",
    "city": "Hafirru",
    "state": "DC",
    "zip": "68010"
  },
  "contact": {
    "phone": "(252) 628-6590",
    "servicePhone": "800574978"
  },
  "birthday": "1988-03-08T21:57:16.575Z",
  "ip": "120.191.49.162",
  "foo": "bar",
  "profile": {
    "about": "Jiger neezit up henew wic douvu di dajfome jop kik me awcam am. Hoh kep ma utjak vargo ugeotoafe weva ucazarva gopo itu iffa ihculik imdog. Ducpifi sipog agefna omi ufrimuz zabwufku wu dokeir gitti tewzas or decizog iwpuz divkosav da pe nitipzo.",
    "bio": "Gad lucoged sajiv juped tuliwa sic kuvuz raba ga rizakcu pu diw tabhep sovebu kawif medmosu regu. Pijahcet dajpi afizo vufaw gudmibwu vav na gijube urreklog waceguc kamnoviwo larrokof ako. Puuvaag wesivot baf awisuwmon minecci nin abipide re ir owududute ha pugsujo noz pi detrov re fuitasi. Fasegpa digih ojurwoc samotiw odike bik izte rirluk huceaje em pif gapab ajnablid nure. Duapelup ikirod aguokro huc nuk top eju ersasze cosparboj buduk pilzigu tonfefosi pugde dowobkez wafpajav."
  },
  "apiKey": "2b6142a9686529239fe7f1e4cdc95f656b975eb1214ef37f13e2fcb7a60bd6d7",
  "currency": {
    "code": "VEF",
    "name": "Venezuela Bolivar"
  }
}