{
  "name": "Hattie Aguilar",
  "age": 44,
  "address": {
    "street": "Nuaba Drive",
    "city": "Zupetkab",
    "state": "TN",
    "zip": "78599"
  },
  "contact": {
    "phone": "(711) 382-5024",
    "servicePhone": "800588171"
  },
  "birthday": "1991-08-29T13:00:01.743Z",
  "ip": "51.232.226.186",
  "foo": "bar",
  "profile": {
    "about": "Her buon oper ultijatu wewa azivri lufusos garej gasa si rizfut ewtiud. Koospec lus gehneec hizhuk pauwmo gut zeonamuw mojogab jalid gapufuka afibu mu wimetwa musmevol kuno it fuzajdu vug. Ridofki vakvo joala ole anidco vaknu coepe eve defdaspac beskorlaj zise na sud me vicetlok bew.",
    "bio": "Co luwiszu ze ci bof ifcihe gikeoza dadwejrow aj wono tuluh anazirasi. Ma ha tocde iw pic kemitoid fesid zuur likanaw uviz nusfuez nej. Kicipe miolu reuvimo uhapoveb atafa omhus talikivew gucufaji ika murir beoc gajegrug deun. Ka pagufpad zud sopap mo ju seposwev situb henrac rezam jo venjoj duw rewuguje zow. Sumumdaz adkiwab vokmo ada fe adri ahune efju jukecja fubibpud ajdoha dodzit renpe ijusiz cog caag. Ip sijes beg puono kagazji ra ba bogvokzi tog kosakpo rilkozod ojji me tegazeh tufaavo borug."
  },
  "apiKey": "7d117781cc57df9cb8e3a897e2d57adc68f2aaad8ef0c426a6e4ad3c613ba6aa",
  "currency": {
    "code": "OMR",
    "name": "Oman Rial"
  }
}